arches/__init__.py
arches/admin.py
arches/apps.py
arches/celery.py
arches/hosts.py
arches/settings.py
arches/settings_docker.py
arches/settings_utils.py
arches/urls.py
arches/version.py
arches/wsgi.py
arches/app/__init__.py
arches/app/const.py
arches/app/signals.py
arches/app/tasks.py
arches/app/datatypes/__init__.py
arches/app/datatypes/base.py
arches/app/datatypes/concept_types.py
arches/app/datatypes/datatypes.py
arches/app/datatypes/url.py
arches/app/datatypes/core/__init__.py
arches/app/datatypes/core/geojson_feature_collection.py
arches/app/datatypes/core/geojson_feature_collection_layer_template.txt
arches/app/datatypes/core/non_localized_string.py
arches/app/datatypes/core/util.py
arches/app/etl_modules/__init__.py
arches/app/etl_modules/base_data_editor.py
arches/app/etl_modules/base_excel_exporter.py
arches/app/etl_modules/base_import_module.py
arches/app/etl_modules/branch_excel_exporter.py
arches/app/etl_modules/branch_excel_importer.py
arches/app/etl_modules/bulk_data_deletion.py
arches/app/etl_modules/bulk_edit_concept.py
arches/app/etl_modules/decorators.py
arches/app/etl_modules/import_single_csv.py
arches/app/etl_modules/jsonld_importer.py
arches/app/etl_modules/save.py
arches/app/etl_modules/tile_excel_exporter.py
arches/app/etl_modules/tile_excel_importer.py
arches/app/functions/__init__.py
arches/app/functions/base.py
arches/app/functions/primary_descriptors.py
arches/app/media/css/accessibility.scss
arches/app/media/css/app.css
arches/app/media/css/arches.scss
arches/app/media/css/base-manager.css
arches/app/media/css/core.scss
arches/app/media/css/edit-history.scss
arches/app/media/css/index-slider-legacy.css
arches/app/media/css/index-slider.css
arches/app/media/css/index.css
arches/app/media/css/jqtree.scss
arches/app/media/css/main.css
arches/app/media/css/nifty.css
arches/app/media/css/package.css
arches/app/media/css/page_404_error3.css
arches/app/media/css/page_job_inner.css
arches/app/media/css/plugins.css
arches-8.0.8.dist-info/licenses/LICENSE.txt
arches-8.0.8.dist-info/METADATA
arches-8.0.8.dist-info/WHEEL
arches-8.0.8.dist-info/entry_points.txt
arches-8.0.8.dist-info/top_level.txt
arches-8.0.8.dist-info/RECORD
