Metadata-Version: 2.4
Name: arches
Version: 8.0.8
Summary: Arches is an open-source, web-based, geospatial information system for cultural heritage inventory and management.
Author: Arches Project
License-Expression: AGPL-3.0-or-later
Project-URL: Homepage, https://archesproject.org/
Project-URL: Documentation, https://arches.readthedocs.io
Project-URL: Repository, https://github.com/archesproject/arches.git
Project-URL: Issues, https://github.com/archesproject/arches/issues
Keywords: django,arches,cultural heritage
Classifier: Development Status :: 5 - Production/Stable
Classifier: Intended Audience :: Developers
Classifier: Intended Audience :: Science/Research
Classifier: Intended Audience :: Information Technology
Classifier: Programming Language :: Python :: 3
Classifier: Programming Language :: Python :: 3 :: Only
Classifier: Programming Language :: Python :: 3.11
Classifier: Programming Language :: Python :: 3.12
Classifier: Programming Language :: Python :: 3.13
Classifier: Framework :: Django
Classifier: Framework :: Django :: 5.2
Requires-Python: >=3.11
License-File: LICENSE.txt
Requires-Dist: arcgis2geojson==2.0.0
Requires-Dist: celery==5.5.0
Requires-Dist: defusedxml==0.7.1
Requires-Dist: Django<6.0.0,>=5.2.3
Requires-Dist: django-celery-results==2.6.0
Requires-Dist: django-cors-headers==4.7.0
Requires-Dist: django-guardian==2.4.0
Requires-Dist: django-hosts==6.0.0
Requires-Dist: django-oauth-toolkit==3.0.1
Requires-Dist: django-pgtrigger==4.15.2
Requires-Dist: django-ratelimit==4.1.0
Requires-Dist: django-recaptcha==4.1.0
Requires-Dist: django-revproxy==0.13.0
Requires-Dist: django-migrate-sql-deux==1.1.1
Requires-Dist: django-webpack-loader==3.1.1
Requires-Dist: edtf==4.0.1
Requires-Dist: elasticsearch<9.0.0,>=8.3.1
Requires-Dist: filetype==1.2.0
Requires-Dist: openpyxl==3.1.5
Requires-Dist: pillow>=7.0.0
Requires-Dist: polib==1.1.1
Requires-Dist: psycopg2==2.9.10
Requires-Dist: pycryptodome<4.0.0,>=3.3.1
Requires-Dist: pyjwt<3,>=2.0.0
Requires-Dist: pyjwt[crypto]
Requires-Dist: PyLD[requests]==1.0.5
Requires-Dist: pyotp>=2.6.0
Requires-Dist: pyprind==2.11.3
Requires-Dist: pyshp==2.1.2
Requires-Dist: python-memcached==1.62
Requires-Dist: python-slugify==7.0.0
Requires-Dist: pytz==2023.3
Requires-Dist: qrcode>=7.3.1
Requires-Dist: rdflib==4.2.2
Requires-Dist: requests-oauthlib==2.0.0
Requires-Dist: requests[security]>=2.32.3
Requires-Dist: semantic-version==2.10.0
Requires-Dist: SPARQLWrapper==1.8.5
Requires-Dist: urllib3<2
Dynamic: license-file
